u3id-0.0.10.dist-info/RECORD
u3id-0.0.10.dist-info/METADATA
u3id-0.0.10.dist-info/LICENSE
u3id-0.0.10.dist-info/WHEEL
u3id-0.0.10.dist-info/top_level.txt
u3id.libs/libkrb5support-ff900cbb.so.0.1
u3id.libs/libcom_err-f788d215.so.2.1
u3id.libs/libkrb5-9480970b.so.3.3
u3id.libs/libk5crypto-19d2ee81.so.3.1
u3id.libs/libselinux-c9aa910a.so.1
u3id.libs/libpcre-863f8bd5.so.1.2.0
u3id.libs/libkeyutils-a0133cb5.so.1.5
u3id.libs/libssl-45d6cc3d.so.1.0.2k
u3id.libs/libgssapi_krb5-a7735118.so.2.2
u3id.libs/libcrypto-608e3dbc.so.1.0.2k
u3id/fallback.py
u3id/_u3id.cpython-311-i386-linux-gnu.so
u3id/__init__.py
