Metadata-Version: 2.1
Name: u3id
Version: 0.0.10
Summary: A user configurable universal id that contains a time component and a chaotic component.
Home-page: https://flowlabs.ai
Author: Tommy Mckinnon
Author-email: tommy@flowlabs.ai
License: MIT
Platform: UNKNOWN
Classifier: Programming Language :: Python :: 3
Classifier: Programming Language :: Python :: 3.6
Classifier: Programming Language :: Python :: 3.7
Classifier: Programming Language :: Python :: 3.8
Classifier: Programming Language :: Python :: 3.9
Classifier: Programming Language :: Python :: 3.10
Classifier: Programming Language :: Python :: 3.11
Classifier: Programming Language :: Python :: Implementation :: CPython
Classifier: Programming Language :: Python :: Implementation :: PyPy
Classifier: Intended Audience :: Developers
License-File: LICENSE
